autodiscover/__init__.py
autodiscover/autodiscover.py
tests/__init__.py
tests/test_autodiscover.py
autodiscover-0.0.3.dist-info/LICENSE
autodiscover-0.0.3.dist-info/METADATA
autodiscover-0.0.3.dist-info/WHEEL
autodiscover-0.0.3.dist-info/top_level.txt
autodiscover-0.0.3.dist-info/RECORD
