Metadata-Version: 2.1
Name: autodiscover
Version: 0.0.3
Summary: Autodiscover modules in python
Home-page: https://github.com/nicolaszein/autodiscover
Author: Nícolas Zein
Author-email: niczein@gmail.com
License: UNKNOWN
Platform: UNKNOWN
Classifier: Programming Language :: Python :: 3
Classifier: License :: OSI Approved :: MIT License
Classifier: Operating System :: OS Independent
Requires-Python: >=3
